markdown_tools/__init__.py
markdown_tools/__main__.py
markdown_tools/uploaders.py
advanced_markdown_tools-0.1.8.dist-info/entry_points.txt
advanced_markdown_tools-0.1.8.dist-info/WHEEL
advanced_markdown_tools-0.1.8.dist-info/METADATA
advanced_markdown_tools-0.1.8.dist-info/RECORD
