Metadata-Version: 2.1
Name: advanced-markdown-tools
Version: 0.1.8
Summary: 
Author: Santiago Basulto
Author-email: santiago.basulto@gmail.com
Requires-Python: >=3.8,<4.0
Classifier: Programming Language :: Python :: 3
Classifier: Programming Language :: Python :: 3.8
Requires-Dist: boto3 (>=1.24.38,<2.0.0)
Requires-Dist: click (>=8.1.3,<9.0.0)
Requires-Dist: requests (>=2.28.1,<3.0.0)
